task3/counter.sv
module counter #(
    parameter WIDTH = 8
)
(

    // interface signals
    input logic vbuddy_preset,
    input logic [WIDTH-1:0] rotary_encoder,
    input logic clk, // clock
    input logic rst, // reset
    input logic en, // counter enable
    output logic [WIDTH-1:0] count // counter output
);

always_ff @ (posedge clk, posedge rst, posedge vbuddy_preset)
    if (vbuddy_preset) count <= rotary_encoder;
    else if (rst) count <= {WIDTH{1'b0}};
    else count <= count + {{WIDTH-1{1'b0}}, en};
endmodule

task3/counter.vcd
$version Generated by VerilatedVcd $end
$date Thu Oct 27 15:36:41 2022 $end
$timescale 1ps $end

 $scope module TOP $end
  $var wire  1 % clk $end
  $var wire  8 ( count [7:0] $end
  $var wire  1 ' en $end
  $var wire  8 $ rotary_encoder [7:0] $end
  $var wire  1 & rst $end
  $var wire  1 # vbuddy_preset $end
  $scope module counter $end
   $var wire 32 ) WIDTH [31:0] $end
   $var wire  1 % clk $end
   $var wire  8 ( count [7:0] $end
   $var wire  1 ' en $end
   $var wire  8 $ rotary_encoder [7:0] $end
   $var wire  1 & rst $end
   $var wire  1 # vbuddy_preset $end
  $upscope $end
 $upscope $end
$enddefinitions $end


#0
0#
b00000000 $
1%
1&
0'
b00000000 (
b00000000000000000000000000001000 )
#1
0%
#2
b01000100 $
1%
#3
0%
#4
1%
#5
0%
#6
1%
0&
#7
0%
#8
1%
#9
0%
#10
1%
#11
0%
#12
1%
1'
#13
0%
#14
1%
b00000001 (
#15
0%
#16
1%
b00000010 (
#17
0%
#18
1%
b00000011 (
#19
0%
#20
1%
b00000100 (
#21
0%
#22
1%
b00000101 (
#23
0%
#24
1#
1%
b00000110 (
#25
0%
b01000100 (
#26
0#
1%
#27
0%
#28
1%
b01000101 (
#29
0%
#30
1%
b01000110 (
#31
0%
#32
b01000101 $
1%
1&
b01000111 (
#33
0%
b00000000 (
#34
b01000111 $
1%
0&
#35
0%
#36
1%
b00000001 (
#37
0%
#38
1#
1%
b00000010 (
#39
0%
b01000111 (
#40
0#
1%
#41
0%
#42
1%
b01001000 (
#43
0%
#44
1%
b01001001 (
#45
0%
#46
1%
b01001010 (
#47
0%
#48
b01001100 $
1%
b01001011 (
#49
0%
#50
b01010010 $
1%
b01001100 (
#51
0%
#52
1%
b01001101 (
#53
0%
#54
1#
1%
b01001110 (
#55
0%
b01010010 (
#56
0#
1%
#57
0%
#58
1%
b01010011 (
#59
0%
#60
1%
b01010100 (
#61
0%
#62
1%
b01010101 (
#63
0%
#64
1%
b01010110 (
#65
0%
#66
1%
b01010111 (
#67
0%
#68
b01011011 $
1%
b01011000 (
#69
0%
#70
b01011101 $
1%
b01011001 (
#71
0%
#72
1#
1%
b01011010 (
#73
0%
b01011101 (
#74
0#
1%
#75
0%
#76
1%
b01011110 (
#77
0%
#78
1%
b01011111 (
#79
0%
#80
b01010011 $
1%
b01100000 (
#81
0%
#82
b01010010 $
1%
b01100001 (
#83
0%
#84
b01001001 $
1%
b01100010 (
#85
0%
#86
b01000110 $
1%
b01100011 (
#87
0%
#88
b01000000 $
1%
b01100100 (
#89
0%
#90
b00110010 $
1%
b01100101 (
#91
0%
#92
b00101011 $
1%
b01100110 (
#93
0%
#94
b00101000 $
1%
b01100111 (
#95
0%
#96
1%
b01101000 (
#97
0%
#98
1#
1%
b01101001 (
#99
0%
b00101000 (
#100
0#
1%
#101
0%
#102
1%
b00101001 (
#103
0%
#104
1%
b00101010 (
#105
0%
#106
1%
b00101011 (
#107
0%
#108
1%
b00101100 (
#109
0%
#110
b00100111 $
1%
b00101101 (
#111
0%
#112
1%
b00101110 (
#113
0%
#114
b00100110 $
1%
b00101111 (
#115
0%
#116
b00100101 $
1%
b00110000 (
#117
0%
#118
1#
1%
b00110001 (
#119
0%
b00100101 (
#120
0#
1%
#121
0%
#122
1%
b00100110 (
#123
0%
#124
1%
b00100111 (
#125
0%
#126
1%
b00101000 (
#127
0%
#128
1%
b00101001 (
#129
0%
#130
1%
b00101010 (
#131
0%
#132
1%
b00101011 (
#133
0%
#134
1%
b00101100 (
#135
0%
#136
1%
b00101101 (
#137
0%
#138
1%
b00101110 (
#139
0%
#140
1%
b00101111 (
#141
0%
#142
1%
b00110000 (
#143
0%
#144
1%
b00110001 (
#145
0%
#146
1%
b00110010 (
#147
0%
#148
1%
b00110011 (
#149
0%
#150
1%
b00110100 (
#151
0%
#152
1%
b00110101 (
#153
0%
#154
1%
b00110110 (
#155
0%
#156
1%
b00110111 (
#157
0%
#158
1%
b00111000 (
#159
0%
#160
1%
b00111001 (
#161
0%
#162
1%
b00111010 (
#163
0%
#164
1%
b00111011 (
#165
0%
#166
1%
b00111100 (
#167
0%
#168
1%
b00111101 (
#169
0%
#170
1%
b00111110 (
#171
0%
#172
1%
b00111111 (
#173
0%
#174
1%
b01000000 (
#175
0%
#176
1%
b01000001 (
#177
0%
#178
1%
b01000010 (
#179
0%
#180
1%
b01000011 (
#181
0%
#182
1%
b01000100 (
#183
0%
#184
1%
b01000101 (
#185
0%
#186
1%
b01000110 (
#187
0%
#188
1%
b01000111 (
#189
0%
#190
1%
b01001000 (
#191
0%
#192
1%
b01001001 (
#193
0%
#194
1%
b01001010 (
#195
0%
#196
1%
b01001011 (
#197
0%
#198
1%
b01001100 (
#199
0%
#200
1%
b01001101 (
#201
0%
#202
1%
b01001110 (
#203
0%
#204
1%
b01001111 (
#205
0%
#206
1%
b01010000 (
#207
0%
#208
1%
b01010001 (
#209
0%
#210
1%
b01010010 (
#211
0%
#212
1%
b01010011 (
#213
0%
#214
1%
b01010100 (
#215
0%
#216
1%
b01010101 (
#217
0%
#218
1%
b01010110 (
#219
0%
#220
1%
b01010111 (
#221
0%
#222
1%
b01011000 (
#223
0%
#224
1%
b01011001 (
#225
0%
#226
1%
b01011010 (
#227
0%
#228
1%
b01011011 (
#229
0%
#230
1%
b01011100 (
#231
0%
#232
1%
b01011101 (
#233
0%
#234
1%
b01011110 (
#235
0%
#236
1%
b01011111 (
#237
0%
#238
1%
b01100000 (
#239
0%
#240
1%
b01100001 (
#241
0%
#242
1%
b01100010 (
#243
0%
#244
1%
b01100011 (
#245
0%
#246
1%
b01100100 (
#247
0%
#248
1%
b01100101 (
#249
0%
#250
1%
b01100110 (
#251
0%
#252
1%
b01100111 (
#253
0%
#254
1%
b01101000 (
#255
0%
#256
1%
b01101001 (
#257
0%
#258
1%
b01101010 (
#259
0%
#260
1%
b01101011 (
#261
0%
#262
1%
b01101100 (
#263
0%
#264
1%
b01101101 (
#265
0%
#266
1%
b01101110 (
#267
0%
#268
1%
b01101111 (
#269
0%
#270
1%
b01110000 (
#271
0%
#272
1%
b01110001 (
#273
0%
#274
1%
b01110010 (
#275
0%
#276
1%
b01110011 (
#277
0%
#278
1%
b01110100 (
#279
0%
#280
1%
b01110101 (
#281
0%
#282
1%
b01110110 (
#283
0%
#284
1%
b01110111 (
#285
0%
#286
1%
b01111000 (
#287
0%
#288
1%
b01111001 (
#289
0%
#290
1%
b01111010 (
#291
0%
#292
1%
b01111011 (
#293
0%
#294
1%
b01111100 (
#295
0%
#296
1%
b01111101 (
#297
0%
#298
1%
b01111110 (
#299
0%
#300
1%
b01111111 (
#301
0%
#302
1%
b10000000 (
#303
0%
#304
1%
b10000001 (
#305
0%
#306
1%
b10000010 (
#307
0%
#308
1%
b10000011 (
#309
0%
#310
1%
b10000100 (
#311
0%
#312
1%
b10000101 (
#313
0%
#314
1%
b10000110 (
#315
0%
#316
1%
b10000111 (
#317
0%
#318
1%
b10001000 (
#319
0%
#320
1%
b10001001 (
#321
0%
#322
1%
b10001010 (
#323
0%
#324
1%
b10001011 (
#325
0%
#326
1%
b10001100 (
#327
0%
#328
1%
b10001101 (
#329
0%
#330
1%
b10001110 (
#331
0%
#332
1%
b10001111 (
#333
0%
#334
1%
b10010000 (
#335
0%
#336
1%
b10010001 (
#337
0%
#338
1%
b10010010 (
#339
0%
#340
1%
b10010011 (
#341
0%
#342
1%
b10010100 (
#343
0%
#344
1%
b10010101 (
#345
0%
#346
1%
b10010110 (
#347
0%
#348
1%
b10010111 (
#349
0%
#350
1%
b10011000 (
#351
0%
#352
1%
b10011001 (
#353
0%
#354
1%
b10011010 (
#355
0%
#356
1%
b10011011 (
#357
0%
#358
1%
b10011100 (
#359
0%
#360
1%
b10011101 (
#361
0%
#362
1%
b10011110 (
#363
0%
#364
1%
b10011111 (
#365
0%
#366
1%
b10100000 (
#367
0%
#368
1%
b10100001 (
#369
0%
#370
1%
b10100010 (
#371
0%
#372
1%
b10100011 (
#373
0%
#374
1%
b10100100 (
#375
0%
#376
1%
b10100101 (
#377
0%
#378
1%
b10100110 (
#379
0%
#380
1%
b10100111 (
#381
0%
#382
1%
b10101000 (
#383
0%
#384
1%
b10101001 (
#385
0%
#386
1%
b10101010 (
#387
0%
#388
1%
b10101011 (
#389
0%
#390
1%
b10101100 (
#391
0%
#392
1%
b10101101 (
#393
0%
#394
1%
b10101110 (
#395
0%
#396
1%
b10101111 (
#397
0%
#398
1%
b10110000 (
#399
0%
#400
1%
b10110001 (
#401
0%
#402
1%
b10110010 (
#403
0%
#404
1%
b10110011 (
#405
0%
#406
1%
b10110100 (
#407
0%
#408
1%
b10110101 (
#409
0%
#410
1%
b10110110 (
#411
0%
#412
1%
b10110111 (
#413
0%
#414
1%
b10111000 (
#415
0%
#416
1%
b10111001 (
#417
0%
#418
1%
b10111010 (
#419
0%
#420
1%
b10111011 (
#421
0%
#422
1%
b10111100 (
#423
0%
#424
1%
b10111101 (
#425
0%
#426
1%
b10111110 (
#427
0%
#428
1%
b10111111 (
#429
0%
#430
1%
b11000000 (
#431
0%
#432
1%
b11000001 (
#433
0%
#434
1%
b11000010 (
#435
0%
#436
1%
b11000011 (
#437
0%
#438
1%
b11000100 (
#439
0%
#440
1%
b11000101 (
#441
0%
#442
1%
b11000110 (
#443
0%
#444
1%
b11000111 (
#445
0%
#446
1%
b11001000 (
#447
0%
#448
1%
b11001001 (
#449
0%
#450
1%
b11001010 (
#451
0%
#452
1%
b11001011 (
#453
0%
#454
1%
b11001100 (
#455
0%
#456
1%
b11001101 (
#457
0%
#458
1%
b11001110 (
#459
0%
#460
1%
b11001111 (
#461
0%
#462
1%
b11010000 (
#463
0%
#464
1%
b11010001 (
#465
0%
#466
1%
b11010010 (
#467
0%
#468
1%
b11010011 (
#469
0%
#470
1%
b11010100 (
#471
0%
#472
1%
b11010101 (
#473
0%
#474
1%
b11010110 (
#475
0%
#476
1%
b11010111 (
#477
0%
#478
1%
b11011000 (
#479
0%
#480
1%
b11011001 (
#481
0%
#482
1%
b11011010 (
#483
0%
#484
1%
b11011011 (
#485
0%
#486
1%
b11011100 (
#487
0%
#488
1#
1%
b11011101 (
#489
0%
b00100101 (
#490
0#
1%
#491
0%
#492
1%
b00100110 (
#493
0%
#494
1%
b00100111 (
#495
0%
#496
1%
b00101000 (
#497
0%
#498
1%
b00101001 (
#499
0%
#500
1%
b00101010 (
#501
0%
#502
1%
b00101011 (
#503
0%
#504
1%
b00101100 (
#505
0%
#506
1%
b00101101 (
#507
0%
#508
1%
b00101110 (
#509
0%
#510
1%
b00101111 (
#511
0%
#512
1%
b00110000 (
#513
0%
#514
1%
b00110001 (
#515
0%
#516
1%
b00110010 (
#517
0%
#518
1%
b00110011 (
#519
0%
#520
1%
b00110100 (
#521
0%
#522
1%
b00110101 (
#523
0%
#524
1%
b00110110 (
#525
0%
#526
1%
b00110111 (
#527
0%
#528
1%
b00111000 (
#529
0%
#530
1%
b00111001 (
#531
0%
#532
1%
b00111010 (
#533
0%
#534
1%
b00111011 (
#535
0%
#536
1%
b00111100 (
#537
0%
#538
1%
b00111101 (
#539
0%
#540
1%
b00111110 (
#541
0%
#542
1%
b00111111 (
#543
0%
#544
b00011101 $
1%
b01000000 (
#545
0%
#546
b00010101 $
1%
b01000001 (
#547
0%
#548
b00010010 $
1%
b01000010 (
#549
0%
#550
b00001101 $
1%
b01000011 (
#551
0%
#552
b00000111 $
1%
b01000100 (
#553
0%
#554
1%
b01000101 (
#555
0%
#556
1%
b01000110 (
#557
0%
#558
1#
1%
b01000111 (
#559
0%
b00000111 (
#560
0#
1%
#561
0%
#562
1%
b00001000 (
#563
0%
#564
1%
b00001001 (
#565
0%
#566
1%
b00001010 (
#567
0%
#568
1%
b00001011 (
#569
0%
#570
1%
b00001100 (
#571
0%
#572
1%
b00001101 (
#573
0%
#574
1%
b00001110 (
#575
0%
#576
1%
b00001111 (
#577
0%
#578
1%
b00010000 (
#579
0%
#580
1%
b00010001 (
#581
0%
#582
1%
b00010010 (
#583
0%
#584
1%
b00010011 (
#585
0%
#586
1%
b00010100 (
#587
0%
#588
1%
b00010101 (
#589
0%
#590
1%
b00010110 (
#591
0%
#592
1%
b00010111 (
#593
0%
#594
1%
b00011000 (
#595
0%
#596
1%
b00011001 (
#597
0%
#598
1%
b00011010 (
